pyetymdict/__init__.py
pyetymdict/dataset.py
pyetymdict/tree.py
pyetymdict/commands/__init__.py
pyetymdict/commands/set.py
pyetymdict-1.0.0.dist-info/LICENSE
pyetymdict-1.0.0.dist-info/METADATA
pyetymdict-1.0.0.dist-info/WHEEL
pyetymdict-1.0.0.dist-info/entry_points.txt
pyetymdict-1.0.0.dist-info/top_level.txt
pyetymdict-1.0.0.dist-info/RECORD
